wagtail_localize_git/__init__.py
wagtail_localize_git/apps.py
wagtail_localize_git/git.py
wagtail_localize_git/importer.py
wagtail_localize_git/models.py
wagtail_localize_git/sync.py
wagtail_localize_git/views.py
wagtail_localize_git/wagtail_hooks.py
wagtail_localize_git/management/__init__.py
wagtail_localize_git/management/commands/__init__.py
wagtail_localize_git/management/commands/sync_git.py
wagtail_localize_git/migrations/0001_initial.py
wagtail_localize_git/migrations/__init__.py
wagtail_localize_git/templates/wagtail_localize_git/dashboard.html
wagtail_localize_git-0.15.0.dist-info/LICENSE
wagtail_localize_git-0.15.0.dist-info/WHEEL
wagtail_localize_git-0.15.0.dist-info/METADATA
wagtail_localize_git-0.15.0.dist-info/RECORD
