Metadata-Version: 2.3
Name: wagtail-localize-git
Version: 0.15.0
Summary: Wagtail Localize integration for Git-based translation services
Keywords: Wagtail,Django,content,review
Author-email: Karl Hobley <karl@torchbox.com>
Maintainer-email: Dan Braghis <dan.braghis@torchbox.com>
Requires-Python: >=3.9
Classifier: Development Status :: 3 - Alpha
Classifier: Intended Audience :: Developers
Classifier: License :: OSI Approved :: BSD License
Classifier: Operating System :: OS Independent
Classifier: Programming Language :: Python
Classifier: Programming Language :: Python :: 3
Classifier: Programming Language :: Python :: 3.9
Classifier: Programming Language :: Python :: 3.10
Classifier: Programming Language :: Python :: 3.11
Classifier: Programming Language :: Python :: 3.12
Classifier: Programming Language :: Python :: 3.13
Classifier: Framework :: Django
Classifier: Framework :: Django :: 4.2
Classifier: Framework :: Django :: 5.0
Classifier: Framework :: Django :: 5.1
Classifier: Framework :: Wagtail
Classifier: Framework :: Wagtail :: 5
Classifier: Framework :: Wagtail :: 6
Requires-Dist: Django>=4.2,<5.2
Requires-Dist: Wagtail>=5.2
Requires-Dist: wagtail-localize>=1.0
Requires-Dist: pygit2>=1.0,<2.0
Requires-Dist: gitpython>=3.0,<4.0
Requires-Dist: toml>=0.10,<0.11
Requires-Dist: dj-database-url>=2.1.0,<3.0 ; extra == "testing"
Requires-Dist: freezegun>=1.4.0,<2.0 ; extra == "testing"
Requires-Dist: coverage>=7.0,<8.0 ; extra == "testing"
Project-URL: Changelog, https://github.com/wagtail/wagtail-localize-git/blob/main/CHANGELOG.md
Project-URL: Source, https://github.com/wagtail/wagtail-localize-git
Provides-Extra: testing
